aladeen_media_indexer/__init__.py
aladeen_media_indexer/metrics.py
aladeen_media_indexer/temperature_index.py
aladeen_media_indexer/utils.py
aladeen_media_indexer-0.3.0.dist-info/METADATA
aladeen_media_indexer-0.3.0.dist-info/WHEEL
aladeen_media_indexer-0.3.0.dist-info/top_level.txt
aladeen_media_indexer-0.3.0.dist-info/RECORD
